{
  "period": "year",
  "bestHours": [
    {
      "hour": 3,
      "avgStatus": 1.751,
      "avgMinutes": 52.83,
      "samples": 177
    },
    {
      "hour": 1,
      "avgStatus": 1.774,
      "avgMinutes": 53.82,
      "samples": 177
    },
    {
      "hour": 23,
      "avgStatus": 1.78,
      "avgMinutes": 53.26,
      "samples": 168
    },
    {
      "hour": 0,
      "avgStatus": 1.787,
      "avgMinutes": 53.72,
      "samples": 183
    },
    {
      "hour": 2,
      "avgStatus": 1.797,
      "avgMinutes": 53.96,
      "samples": 177
    },
    {
      "hour": 22,
      "avgStatus": 1.803,
      "avgMinutes": 54.08,
      "samples": 183
    },
    {
      "hour": 4,
      "avgStatus": 1.808,
      "avgMinutes": 53.73,
      "samples": 177
    },
    {
      "hour": 5,
      "avgStatus": 1.876,
      "avgMinutes": 55.6,
      "samples": 177
    },
    {
      "hour": 16,
      "avgStatus": 1.898,
      "avgMinutes": 56.63,
      "samples": 166
    },
    {
      "hour": 10,
      "avgStatus": 1.934,
      "avgMinutes": 56.48,
      "samples": 166
    },
    {
      "hour": 13,
      "avgStatus": 1.946,
      "avgMinutes": 55.19,
      "samples": 148
    },
    {
      "hour": 8,
      "avgStatus": 1.949,
      "avgMinutes": 57.24,
      "samples": 176
    }
  ],
  "areaRank": [
    {
      "areaNameEn": "First Floor Tawaf",
      "avgStatus": 1.727,
      "avgMinutes": 71.79,
      "availabilityPct": 100.0,
      "samples": 623
    },
    {
      "areaNameEn": "First Floor Sa'i",
      "avgStatus": 1.825,
      "avgMinutes": 38.35,
      "availabilityPct": 100.0,
      "samples": 623
    },
    {
      "areaNameEn": "Second Floor Tawaf",
      "avgStatus": 1.933,
      "avgMinutes": 75.51,
      "availabilityPct": 100.0,
      "samples": 623
    },
    {
      "areaNameEn": "Second Floor Sa'i",
      "avgStatus": 1.945,
      "avgMinutes": 34.3,
      "availabilityPct": 79.78,
      "samples": 623
    },
    {
      "areaNameEn": "Roof Tawaf",
      "avgStatus": 1.978,
      "avgMinutes": 64.9,
      "availabilityPct": 79.94,
      "samples": 623
    },
    {
      "areaNameEn": "Ground Floor Sa'i",
      "avgStatus": 2.226,
      "avgMinutes": 52.26,
      "availabilityPct": 100.0,
      "samples": 623
    },
    {
      "areaNameEn": "Mataf Ground Floor (Around Kaaba)",
      "avgStatus": 2.726,
      "avgMinutes": 55.91,
      "availabilityPct": 100.0,
      "samples": 623
    }
  ]
}