{
  "period": "year",
  "bestHours": [
    {
      "hour": 3,
      "avgStatus": 1.738,
      "avgMinutes": 52.68,
      "samples": 183
    },
    {
      "hour": 1,
      "avgStatus": 1.76,
      "avgMinutes": 53.64,
      "samples": 183
    },
    {
      "hour": 23,
      "avgStatus": 1.764,
      "avgMinutes": 53.09,
      "samples": 174
    },
    {
      "hour": 0,
      "avgStatus": 1.772,
      "avgMinutes": 53.54,
      "samples": 189
    },
    {
      "hour": 2,
      "avgStatus": 1.781,
      "avgMinutes": 53.78,
      "samples": 183
    },
    {
      "hour": 22,
      "avgStatus": 1.788,
      "avgMinutes": 53.9,
      "samples": 189
    },
    {
      "hour": 4,
      "avgStatus": 1.792,
      "avgMinutes": 53.56,
      "samples": 183
    },
    {
      "hour": 5,
      "avgStatus": 1.858,
      "avgMinutes": 55.37,
      "samples": 183
    },
    {
      "hour": 16,
      "avgStatus": 1.884,
      "avgMinutes": 56.45,
      "samples": 172
    },
    {
      "hour": 10,
      "avgStatus": 1.915,
      "avgMinutes": 56.11,
      "samples": 176
    },
    {
      "hour": 9,
      "avgStatus": 1.933,
      "avgMinutes": 56.66,
      "samples": 178
    },
    {
      "hour": 8,
      "avgStatus": 1.94,
      "avgMinutes": 57.2,
      "samples": 182
    }
  ],
  "areaRank": [
    {
      "areaNameEn": "First Floor Tawaf",
      "avgStatus": 1.707,
      "avgMinutes": 71.4,
      "availabilityPct": 100.0,
      "samples": 651
    },
    {
      "areaNameEn": "First Floor Sa'i",
      "avgStatus": 1.803,
      "avgMinutes": 38.13,
      "availabilityPct": 100.0,
      "samples": 651
    },
    {
      "areaNameEn": "Second Floor Tawaf",
      "avgStatus": 1.922,
      "avgMinutes": 75.25,
      "availabilityPct": 100.0,
      "samples": 651
    },
    {
      "areaNameEn": "Roof Tawaf",
      "avgStatus": 1.994,
      "avgMinutes": 64.77,
      "availabilityPct": 79.11,
      "samples": 651
    },
    {
      "areaNameEn": "Second Floor Sa'i",
      "avgStatus": 2.023,
      "avgMinutes": 34.32,
      "availabilityPct": 76.8,
      "samples": 651
    },
    {
      "areaNameEn": "Ground Floor Sa'i",
      "avgStatus": 2.214,
      "avgMinutes": 52.14,
      "availabilityPct": 100.0,
      "samples": 651
    },
    {
      "areaNameEn": "Mataf Ground Floor (Around Kaaba)",
      "avgStatus": 2.7,
      "avgMinutes": 55.53,
      "availabilityPct": 100.0,
      "samples": 651
    }
  ]
}