{
  "period": "year",
  "bestHours": [
    {
      "hour": 3,
      "avgStatus": 1.782,
      "avgMinutes": 53.16,
      "samples": 165
    },
    {
      "hour": 1,
      "avgStatus": 1.806,
      "avgMinutes": 54.22,
      "samples": 165
    },
    {
      "hour": 23,
      "avgStatus": 1.814,
      "avgMinutes": 53.63,
      "samples": 156
    },
    {
      "hour": 0,
      "avgStatus": 1.819,
      "avgMinutes": 54.09,
      "samples": 171
    },
    {
      "hour": 2,
      "avgStatus": 1.83,
      "avgMinutes": 54.37,
      "samples": 165
    },
    {
      "hour": 22,
      "avgStatus": 1.83,
      "avgMinutes": 54.4,
      "samples": 171
    },
    {
      "hour": 4,
      "avgStatus": 1.842,
      "avgMinutes": 54.13,
      "samples": 165
    },
    {
      "hour": 16,
      "avgStatus": 1.923,
      "avgMinutes": 57.0,
      "samples": 155
    },
    {
      "hour": 5,
      "avgStatus": 1.925,
      "avgMinutes": 56.21,
      "samples": 159
    },
    {
      "hour": 13,
      "avgStatus": 1.964,
      "avgMinutes": 55.42,
      "samples": 138
    },
    {
      "hour": 10,
      "avgStatus": 1.968,
      "avgMinutes": 56.97,
      "samples": 155
    },
    {
      "hour": 14,
      "avgStatus": 1.971,
      "avgMinutes": 56.11,
      "samples": 139
    }
  ],
  "areaRank": [
    {
      "areaNameEn": "Second Floor Sa'i",
      "avgStatus": 1.758,
      "avgMinutes": 34.3,
      "availabilityPct": 87.04,
      "samples": 571
    },
    {
      "areaNameEn": "First Floor Tawaf",
      "avgStatus": 1.772,
      "avgMinutes": 72.9,
      "availabilityPct": 100.0,
      "samples": 571
    },
    {
      "areaNameEn": "First Floor Sa'i",
      "avgStatus": 1.895,
      "avgMinutes": 39.05,
      "availabilityPct": 100.0,
      "samples": 571
    },
    {
      "areaNameEn": "Second Floor Tawaf",
      "avgStatus": 1.974,
      "avgMinutes": 76.51,
      "availabilityPct": 100.0,
      "samples": 571
    },
    {
      "areaNameEn": "Roof Tawaf",
      "avgStatus": 1.989,
      "avgMinutes": 65.52,
      "availabilityPct": 80.39,
      "samples": 571
    },
    {
      "areaNameEn": "Ground Floor Sa'i",
      "avgStatus": 2.25,
      "avgMinutes": 52.5,
      "availabilityPct": 100.0,
      "samples": 571
    },
    {
      "areaNameEn": "Mataf Ground Floor (Around Kaaba)",
      "avgStatus": 2.785,
      "avgMinutes": 56.77,
      "availabilityPct": 100.0,
      "samples": 571
    }
  ]
}